{
  "2025-08-10 15:21:57 -0400": {
    "date": "2025-08-10 15:21:57 -0400",
    "type": "daily",
    "hours": 4,
    "cost": 1200,
    "commits": 1,
    "deployments": 0,
    "filesModified": 5,
    "linesChanged": 672,
    "authors": [
      "SirsiMaster"
    ],
    "technologies": [
      "CSS",
      "JavaScript",
      "HTML"
    ],
    "achievements": [
      "Major code addition: 672 lines added"
    ]
  },
  "2025-08-22 15:34:59 -0400": {
    "date": "2025-08-22 15:34:59 -0400",
    "type": "daily",
    "hours": 4,
    "cost": 1200,
    "commits": 1,
    "deployments": 0,
    "filesModified": 3,
    "linesChanged": 1985,
    "authors": [
      "SirsiMaster"
    ],
    "technologies": [
      "CSS",
      "JavaScript",
      "HTML"
    ],
    "achievements": [
      "Major code addition: 2149 lines added"
    ]
  },
  "2025-08-22 15:39:09 -0400": {
    "date": "2025-08-22 15:39:09 -0400",
    "type": "daily",
    "hours": 1.48,
    "cost": 444,
    "commits": 1,
    "deployments": 0,
    "filesModified": 1,
    "linesChanged": 120,
    "authors": [
      "SirsiMaster"
    ],
    "technologies": [],
    "achievements": []
  },
  "2025-08-22 16:29:13 -0400": {
    "date": "2025-08-22 16:29:13 -0400",
    "type": "daily",
    "hours": 4,
    "cost": 1200,
    "commits": 1,
    "deployments": 0,
    "filesModified": 16,
    "linesChanged": 3633,
    "authors": [
      "SirsiMaster"
    ],
    "technologies": [
      "GitHub"
    ],
    "achievements": [
      "Major code addition: 3641 lines added"
    ]
  },
  "2025-08-22 16:32:18 -0400": {
    "date": "2025-08-22 16:32:18 -0400",
    "type": "daily",
    "hours": 0.5,
    "cost": 150,
    "commits": 1,
    "deployments": 0,
    "filesModified": 1,
    "linesChanged": 1,
    "authors": [
      "SirsiMaster"
    ],
    "technologies": [],
    "achievements": []
  },
  "2025-08-22 16:32:26 -0400": {
    "date": "2025-08-22 16:32:26 -0400",
    "type": "daily",
    "hours": 0.25,
    "cost": 75,
    "commits": 1,
    "deployments": 0,
    "filesModified": 1,
    "linesChanged": -1,
    "authors": [
      "SirsiMaster"
    ],
    "technologies": [],
    "achievements": []
  },
  "2025-08-22 16:35:17 -0400": {
    "date": "2025-08-22 16:35:17 -0400",
    "type": "daily",
    "hours": 1.445,
    "cost": 434,
    "commits": 1,
    "deployments": 0,
    "filesModified": 1,
    "linesChanged": 289,
    "authors": [
      "SirsiMaster"
    ],
    "technologies": [],
    "achievements": []
  },
  "2025-08-22 17:21:46 -0400": {
    "date": "2025-08-22 17:21:46 -0400",
    "type": "daily",
    "hours": 4,
    "cost": 1200,
    "commits": 1,
    "deployments": 0,
    "filesModified": 7,
    "linesChanged": 4192,
    "authors": [
      "SirsiMaster"
    ],
    "technologies": [
      "GitHub",
      "HTML"
    ],
    "achievements": [
      "Feature: add AI micro-flipping platform and CEO dashboard"
    ]
  },
  "2025-08-22 17:24:59 -0400": {
    "date": "2025-08-22 17:24:59 -0400",
    "type": "daily",
    "hours": 4,
    "cost": 1200,
    "commits": 1,
    "deployments": 0,
    "filesModified": 3,
    "linesChanged": 993,
    "authors": [
      "SirsiMaster"
    ],
    "technologies": [
      "HTML",
      "GitHub"
    ],
    "achievements": [
      "Major code addition: 998 lines added"
    ]
  },
  "2025-08-22 17:33:04 -0400": {
    "date": "2025-08-22 17:33:04 -0400",
    "type": "daily",
    "hours": 4,
    "cost": 1200,
    "commits": 1,
    "deployments": 0,
    "filesModified": 3,
    "linesChanged": -949,
    "authors": [
      "SirsiMaster"
    ],
    "technologies": [
      "HTML"
    ],
    "achievements": []
  },
  "2025-08-22 17:51:40 -0400": {
    "date": "2025-08-22 17:51:40 -0400",
    "type": "daily",
    "hours": 4,
    "cost": 1200,
    "commits": 1,
    "deployments": 0,
    "filesModified": 2,
    "linesChanged": 1197,
    "authors": [
      "SirsiMaster"
    ],
    "technologies": [
      "HTML"
    ],
    "achievements": [
      "Feature: Add light theme and interactive dashboard"
    ]
  },
  "2025-08-22 18:00:25 -0400": {
    "date": "2025-08-22 18:00:25 -0400",
    "type": "daily",
    "hours": 3.89,
    "cost": 1167,
    "commits": 1,
    "deployments": 0,
    "filesModified": 1,
    "linesChanged": 387,
    "authors": [
      "SirsiMaster"
    ],
    "technologies": [
      "HTML"
    ],
    "achievements": [
      "Feature: Add comprehensive feature checklist sidebar"
    ]
  },
  "2025-08-26 14:46:31 -0400": {
    "date": "2025-08-26 14:46:31 -0400",
    "type": "daily",
    "hours": 4,
    "cost": 1200,
    "commits": 1,
    "deployments": 0,
    "filesModified": 10,
    "linesChanged": 8855,
    "authors": [
      "SirsiMaster"
    ],
    "technologies": [
      "HTML"
    ],
    "achievements": [
      "Feature: add executive dashboard suite"
    ]
  },
  "2025-08-26 20:42:10 -0400": {
    "date": "2025-08-26 20:42:10 -0400",
    "type": "daily",
    "hours": 4,
    "cost": 1200,
    "commits": 1,
    "deployments": 0,
    "filesModified": 15,
    "linesChanged": 5131,
    "authors": [
      "SirsiMaster"
    ],
    "technologies": [
      "HTML"
    ],
    "achievements": [
      "Major code addition: 5197 lines added"
    ]
  },
  "2025-08-26 22:42:07 -0400": {
    "date": "2025-08-26 22:42:07 -0400",
    "type": "daily",
    "hours": 0.5,
    "cost": 150,
    "commits": 1,
    "deployments": 0,
    "filesModified": 9,
    "linesChanged": 0,
    "authors": [
      "SirsiMaster"
    ],
    "technologies": [
      "HTML"
    ],
    "achievements": []
  },
  "2025-08-27 12:27:38 -0400": {
    "date": "2025-08-27 12:27:38 -0400",
    "type": "daily",
    "hours": 4,
    "cost": 1200,
    "commits": 1,
    "deployments": 0,
    "filesModified": 12,
    "linesChanged": -478,
    "authors": [
      "SirsiMaster"
    ],
    "technologies": [
      "HTML",
      "CSS"
    ],
    "achievements": [
      "Completed: implement unified Assiduous design system"
    ]
  },
  "2025-08-27 12:31:10 -0400": {
    "date": "2025-08-27 12:31:10 -0400",
    "type": "daily",
    "hours": 0.5266666666666666,
    "cost": 158,
    "commits": 1,
    "deployments": 0,
    "filesModified": 1,
    "linesChanged": 3,
    "authors": [
      "SirsiMaster"
    ],
    "technologies": [
      "HTML"
    ],
    "achievements": []
  },
  "2025-08-27 13:49:19 -0400": {
    "date": "2025-08-27 13:49:19 -0400",
    "type": "daily",
    "hours": 4,
    "cost": 1200,
    "commits": 1,
    "deployments": 0,
    "filesModified": 1,
    "linesChanged": 93,
    "authors": [
      "SirsiMaster"
    ],
    "technologies": [
      "HTML"
    ],
    "achievements": []
  },
  "2025-08-29 16:02:38 -0400": {
    "date": "2025-08-29 16:02:38 -0400",
    "type": "daily",
    "hours": 0.5,
    "cost": 150,
    "commits": 1,
    "deployments": 0,
    "filesModified": 1,
    "linesChanged": 25,
    "authors": [
      "SirsiMaster"
    ],
    "technologies": [
      "CSS"
    ],
    "achievements": []
  },
  "2025-08-29 16:02:50 -0400": {
    "date": "2025-08-29 16:02:50 -0400",
    "type": "daily",
    "hours": 0.5,
    "cost": 150,
    "commits": 1,
    "deployments": 0,
    "filesModified": 1,
    "linesChanged": 11,
    "authors": [
      "SirsiMaster"
    ],
    "technologies": [
      "HTML"
    ],
    "achievements": []
  },
  "2025-08-29 16:03:03 -0400": {
    "date": "2025-08-29 16:03:03 -0400",
    "type": "daily",
    "hours": 4,
    "cost": 1200,
    "commits": 1,
    "deployments": 0,
    "filesModified": 4,
    "linesChanged": -5234,
    "authors": [
      "SirsiMaster"
    ],
    "technologies": [
      "HTML"
    ],
    "achievements": []
  },
  "2025-08-29 16:03:14 -0400": {
    "date": "2025-08-29 16:03:14 -0400",
    "type": "daily",
    "hours": 1.77,
    "cost": 531,
    "commits": 1,
    "deployments": 0,
    "filesModified": 2,
    "linesChanged": 113,
    "authors": [
      "SirsiMaster"
    ],
    "technologies": [
      "HTML"
    ],
    "achievements": [
      "Feature: Enhance landing page design and navigation"
    ]
  },
  "2025-08-29 16:04:34 -0400": {
    "date": "2025-08-29 16:04:34 -0400",
    "type": "daily",
    "hours": 0.25,
    "cost": 75,
    "commits": 1,
    "deployments": 1,
    "filesModified": 1,
    "linesChanged": 22,
    "authors": [
      "SirsiMaster"
    ],
    "technologies": [],
    "achievements": []
  },
  "2025-08-29 16:05:52 -0400": {
    "date": "2025-08-29 16:05:52 -0400",
    "type": "daily",
    "hours": 0.25,
    "cost": 75,
    "commits": 1,
    "deployments": 0,
    "filesModified": 1,
    "linesChanged": 35,
    "authors": [
      "SirsiMaster"
    ],
    "technologies": [],
    "achievements": []
  },
  "2025-08-29 16:36:31 -0400": {
    "date": "2025-08-29 16:36:31 -0400",
    "type": "daily",
    "hours": 4,
    "cost": 1200,
    "commits": 1,
    "deployments": 0,
    "filesModified": 5,
    "linesChanged": 822,
    "authors": [
      "SirsiMaster"
    ],
    "technologies": [
      "HTML"
    ],
    "achievements": [
      "Feature: Redesign Knowledge Base with full functionality"
    ]
  },
  "2025-08-29 16:41:55 -0400": {
    "date": "2025-08-29 16:41:55 -0400",
    "type": "daily",
    "hours": 4,
    "cost": 1200,
    "commits": 1,
    "deployments": 0,
    "filesModified": 2,
    "linesChanged": 595,
    "authors": [
      "SirsiMaster"
    ],
    "technologies": [
      "HTML"
    ],
    "achievements": [
      "Feature: Complete UI/UX improvements across platform"
    ]
  },
  "2025-08-29 17:00:26 -0400": {
    "date": "2025-08-29 17:00:26 -0400",
    "type": "daily",
    "hours": 4,
    "cost": 1200,
    "commits": 1,
    "deployments": 0,
    "filesModified": 2,
    "linesChanged": 80,
    "authors": [
      "SirsiMaster"
    ],
    "technologies": [
      "HTML"
    ],
    "achievements": []
  },
  "2025-08-29 17:19:12 -0400": {
    "date": "2025-08-29 17:19:12 -0400",
    "type": "daily",
    "hours": 4,
    "cost": 1200,
    "commits": 1,
    "deployments": 0,
    "filesModified": 5,
    "linesChanged": 1516,
    "authors": [
      "SirsiMaster"
    ],
    "technologies": [
      "HTML"
    ],
    "achievements": [
      "Major code addition: 2287 lines added"
    ]
  },
  "2025-08-29 17:29:00 -0400": {
    "date": "2025-08-29 17:29:00 -0400",
    "type": "daily",
    "hours": 0.5,
    "cost": 150,
    "commits": 1,
    "deployments": 0,
    "filesModified": 1,
    "linesChanged": 4,
    "authors": [
      "SirsiMaster"
    ],
    "technologies": [
      "HTML"
    ],
    "achievements": []
  },
  "2025-08-29 20:34:11 -0400": {
    "date": "2025-08-29 20:34:11 -0400",
    "type": "daily",
    "hours": 4,
    "cost": 1200,
    "commits": 1,
    "deployments": 0,
    "filesModified": 29,
    "linesChanged": 9321,
    "authors": [
      "SirsiMaster"
    ],
    "technologies": [
      "GitHub",
      "HTML"
    ],
    "achievements": [
      "Feature: Add real GitHub data and unified platform"
    ]
  },
  "2025-08-29 20:41:36 -0400": {
    "date": "2025-08-29 20:41:36 -0400",
    "type": "daily",
    "hours": 1.39,
    "cost": 417,
    "commits": 1,
    "deployments": 0,
    "filesModified": 2,
    "linesChanged": 139,
    "authors": [
      "SirsiMaster"
    ],
    "technologies": [
      "HTML"
    ],
    "achievements": [
      "Feature: Add comprehensive docs hub with all blueprints"
    ]
  },
  "2025-08-29 20:49:33 -0400": {
    "date": "2025-08-29 20:49:33 -0400",
    "type": "daily",
    "hours": 3.47,
    "cost": 1041,
    "commits": 1,
    "deployments": 0,
    "filesModified": 1,
    "linesChanged": 337,
    "authors": [
      "SirsiMaster"
    ],
    "technologies": [
      "HTML"
    ],
    "achievements": [
      "Feature: Add beautiful HTML markdown viewer for docs"
    ]
  },
  "2025-08-30 17:04:00 -0400": {
    "date": "2025-08-30 17:04:00 -0400",
    "type": "daily",
    "hours": 0.63,
    "cost": 189,
    "commits": 1,
    "deployments": 1,
    "filesModified": 1,
    "linesChanged": 126,
    "authors": [
      "SirsiMaster"
    ],
    "technologies": [],
    "achievements": []
  },
  "2025-08-30 18:32:23 -0400": {
    "date": "2025-08-30 18:32:23 -0400",
    "type": "daily",
    "hours": 4,
    "cost": 1200,
    "commits": 1,
    "deployments": 0,
    "filesModified": 8,
    "linesChanged": 1445,
    "authors": [
      "SirsiMaster"
    ],
    "technologies": [
      "HTML",
      "JavaScript"
    ],
    "achievements": [
      "Major code addition: 1565 lines added"
    ]
  },
  "2025-08-30 18:39:58 -0400": {
    "date": "2025-08-30 18:39:58 -0400",
    "type": "daily",
    "hours": 0.75,
    "cost": 225,
    "commits": 1,
    "deployments": 0,
    "filesModified": 1,
    "linesChanged": 0,
    "authors": [
      "SirsiMaster"
    ],
    "technologies": [
      "HTML"
    ],
    "achievements": []
  },
  "2025-08-30 18:49:48 -0400": {
    "date": "2025-08-30 18:49:48 -0400",
    "type": "daily",
    "hours": 1.975,
    "cost": 593,
    "commits": 1,
    "deployments": 0,
    "filesModified": 1,
    "linesChanged": 395,
    "authors": [
      "SirsiMaster"
    ],
    "technologies": [],
    "achievements": []
  },
  "2025-08-30 19:00:43 -0400": {
    "date": "2025-08-30 19:00:43 -0400",
    "type": "daily",
    "hours": 4,
    "cost": 1200,
    "commits": 1,
    "deployments": 0,
    "filesModified": 6,
    "linesChanged": 449,
    "authors": [
      "SirsiMaster"
    ],
    "technologies": [
      "JavaScript",
      "GitHub"
    ],
    "achievements": [
      "Feature: add GitHub-based database system"
    ]
  },
  "2025-08-30 19:03:07 -0400": {
    "date": "2025-08-30 19:03:07 -0400",
    "type": "daily",
    "hours": 4,
    "cost": 1200,
    "commits": 1,
    "deployments": 0,
    "filesModified": 4,
    "linesChanged": 863,
    "authors": [
      "SirsiMaster"
    ],
    "technologies": [
      "JavaScript"
    ],
    "achievements": [
      "Feature: add advanced database features"
    ]
  },
  "2025-08-30 19:06:20 -0400": {
    "date": "2025-08-30 19:06:20 -0400",
    "type": "daily",
    "hours": 3.46,
    "cost": 1038,
    "commits": 1,
    "deployments": 0,
    "filesModified": 5,
    "linesChanged": 342,
    "authors": [
      "SirsiMaster"
    ],
    "technologies": [
      "GitHub",
      "JavaScript"
    ],
    "achievements": [
      "Feature: add data encryption and access controls"
    ]
  },
  "2025-08-30 19:09:19 -0400": {
    "date": "2025-08-30 19:09:19 -0400",
    "type": "daily",
    "hours": 2.53,
    "cost": 759,
    "commits": 1,
    "deployments": 0,
    "filesModified": 2,
    "linesChanged": 506,
    "authors": [
      "SirsiMaster"
    ],
    "technologies": [],
    "achievements": [
      "Completed: add security implementation documentation"
    ]
  },
  "2025-08-30 19:11:39 -0400": {
    "date": "2025-08-30 19:11:39 -0400",
    "type": "daily",
    "hours": 0.5533333333333333,
    "cost": 166,
    "commits": 1,
    "deployments": 0,
    "filesModified": 2,
    "linesChanged": 59,
    "authors": [
      "SirsiMaster"
    ],
    "technologies": [
      "JavaScript",
      "GitHub"
    ],
    "achievements": []
  },
  "2025-08-30 19:12:31 -0400": {
    "date": "2025-08-30 19:12:31 -0400",
    "type": "daily",
    "hours": 1,
    "cost": 300,
    "commits": 1,
    "deployments": 0,
    "filesModified": 2,
    "linesChanged": 7,
    "authors": [
      "SirsiMaster"
    ],
    "technologies": [
      "GitHub"
    ],
    "achievements": [
      "Feature: add environment secrets"
    ]
  },
  "2025-08-30 19:13:28 -0400": {
    "date": "2025-08-30 19:13:28 -0400",
    "type": "daily",
    "hours": 0.25,
    "cost": 75,
    "commits": 1,
    "deployments": 0,
    "filesModified": 1,
    "linesChanged": -7,
    "authors": [
      "SirsiMaster"
    ],
    "technologies": [
      "GitHub"
    ],
    "achievements": []
  },
  "2025-08-30 19:14:36 -0400": {
    "date": "2025-08-30 19:14:36 -0400",
    "type": "daily",
    "hours": 0.5,
    "cost": 150,
    "commits": 1,
    "deployments": 0,
    "filesModified": 1,
    "linesChanged": 0,
    "authors": [
      "SirsiMaster"
    ],
    "technologies": [
      "GitHub"
    ],
    "achievements": []
  },
  "2025-08-30 19:17:27 -0400": {
    "date": "2025-08-30 19:17:27 -0400",
    "type": "daily",
    "hours": 0.5,
    "cost": 150,
    "commits": 1,
    "deployments": 0,
    "filesModified": 3,
    "linesChanged": 1,
    "authors": [
      "SirsiMaster"
    ],
    "technologies": [
      "JavaScript",
      "GitHub"
    ],
    "achievements": []
  },
  "2025-08-30 19:18:03 -0400": {
    "date": "2025-08-30 19:18:03 -0400",
    "type": "daily",
    "hours": 0.25,
    "cost": 75,
    "commits": 1,
    "deployments": 0,
    "filesModified": 1,
    "linesChanged": 1,
    "authors": [
      "SirsiMaster"
    ],
    "technologies": [
      "Node.js"
    ],
    "achievements": []
  },
  "2025-08-30 19:18:42 -0400": {
    "date": "2025-08-30 19:18:42 -0400",
    "type": "daily",
    "hours": 0.5,
    "cost": 150,
    "commits": 1,
    "deployments": 0,
    "filesModified": 1,
    "linesChanged": 13,
    "authors": [
      "SirsiMaster"
    ],
    "technologies": [
      "Node.js"
    ],
    "achievements": []
  },
  "2025-08-30 19:19:29 -0400": {
    "date": "2025-08-30 19:19:29 -0400",
    "type": "daily",
    "hours": 0.5,
    "cost": 150,
    "commits": 1,
    "deployments": 0,
    "filesModified": 1,
    "linesChanged": 0,
    "authors": [
      "SirsiMaster"
    ],
    "technologies": [
      "GitHub"
    ],
    "achievements": []
  },
  "2025-08-30 19:20:16 -0400": {
    "date": "2025-08-30 19:20:16 -0400",
    "type": "daily",
    "hours": 0.5,
    "cost": 150,
    "commits": 1,
    "deployments": 0,
    "filesModified": 1,
    "linesChanged": 0,
    "authors": [
      "SirsiMaster"
    ],
    "technologies": [
      "GitHub"
    ],
    "achievements": []
  },
  "2025-08-30 19:21:37 -0400": {
    "date": "2025-08-30 19:21:37 -0400",
    "type": "daily",
    "hours": 2.2,
    "cost": 660,
    "commits": 1,
    "deployments": 0,
    "filesModified": 2,
    "linesChanged": 218,
    "authors": [
      "SirsiMaster"
    ],
    "technologies": [
      "JavaScript",
      "GitHub"
    ],
    "achievements": [
      "Feature: enhance database operations"
    ]
  },
  "2025-08-30 19:22:39 -0400": {
    "date": "2025-08-30 19:22:39 -0400",
    "type": "daily",
    "hours": 0.5,
    "cost": 150,
    "commits": 1,
    "deployments": 0,
    "filesModified": 1,
    "linesChanged": 1,
    "authors": [
      "SirsiMaster"
    ],
    "technologies": [
      "JavaScript",
      "GitHub"
    ],
    "achievements": []
  },
  "2025-08-30 23:22:59 +0000": {
    "date": "2025-08-30 23:22:59 +0000",
    "type": "daily",
    "hours": 0.5,
    "cost": 150,
    "commits": 1,
    "deployments": 0,
    "filesModified": 1,
    "linesChanged": -6,
    "authors": [
      "GitHub Action"
    ],
    "technologies": [],
    "achievements": []
  },
  "2025-08-30 19:25:47 -0400": {
    "date": "2025-08-30 19:25:47 -0400",
    "type": "daily",
    "hours": 4,
    "cost": 1200,
    "commits": 1,
    "deployments": 0,
    "filesModified": 3,
    "linesChanged": 691,
    "authors": [
      "SirsiMaster"
    ],
    "technologies": [
      "Firebase",
      "Node.js",
      "JavaScript"
    ],
    "achievements": [
      "Feature: integrate Firebase/Firestore"
    ]
  },
  "2025-08-30 19:29:32 -0400": {
    "date": "2025-08-30 19:29:32 -0400",
    "type": "daily",
    "hours": 4,
    "cost": 1200,
    "commits": 1,
    "deployments": 0,
    "filesModified": 6,
    "linesChanged": 509,
    "authors": [
      "SirsiMaster"
    ],
    "technologies": [
      "JavaScript",
      "Firebase"
    ],
    "achievements": [
      "Feature: implement REST API with tests"
    ]
  },
  "2025-08-30 19:35:44 -0400": {
    "date": "2025-08-30 19:35:44 -0400",
    "type": "daily",
    "hours": 0.255,
    "cost": 77,
    "commits": 1,
    "deployments": 0,
    "filesModified": 2,
    "linesChanged": 29,
    "authors": [
      "SirsiMaster"
    ],
    "technologies": [],
    "achievements": [
      "Completed: update security docs and implementation plan"
    ]
  },
  "2025-08-30 19:41:09 -0400": {
    "date": "2025-08-30 19:41:09 -0400",
    "type": "daily",
    "hours": 1.6133333333333333,
    "cost": 484,
    "commits": 1,
    "deployments": 0,
    "filesModified": 2,
    "linesChanged": 162,
    "authors": [
      "SirsiMaster"
    ],
    "technologies": [
      "Firebase",
      "GitHub",
      "JavaScript"
    ],
    "achievements": []
  },
  "2025-09-01 12:06:01 -0400": {
    "date": "2025-09-01 12:06:01 -0400",
    "type": "daily",
    "hours": 1.225,
    "cost": 368,
    "commits": 1,
    "deployments": 0,
    "filesModified": 2,
    "linesChanged": 187,
    "authors": [
      "SirsiMaster"
    ],
    "technologies": [
      "Firebase"
    ],
    "achievements": []
  },
  "2025-09-01 12:08:55 -0400": {
    "date": "2025-09-01 12:08:55 -0400",
    "type": "daily",
    "hours": 0.5,
    "cost": 150,
    "commits": 1,
    "deployments": 0,
    "filesModified": 1,
    "linesChanged": 0,
    "authors": [
      "SirsiMaster"
    ],
    "technologies": [
      "HTML"
    ],
    "achievements": []
  },
  "2025-09-01 12:13:33 -0400": {
    "date": "2025-09-01 12:13:33 -0400",
    "type": "daily",
    "hours": 0.3,
    "cost": 90,
    "commits": 1,
    "deployments": 0,
    "filesModified": 1,
    "linesChanged": 60,
    "authors": [
      "SirsiMaster"
    ],
    "technologies": [],
    "achievements": []
  },
  "2025-09-01 12:19:56 -0400": {
    "date": "2025-09-01 12:19:56 -0400",
    "type": "daily",
    "hours": 0.85,
    "cost": 255,
    "commits": 1,
    "deployments": 0,
    "filesModified": 37,
    "linesChanged": 0,
    "authors": [
      "SirsiMaster"
    ],
    "technologies": [
      "HTML",
      "CSS"
    ],
    "achievements": []
  },
  "2025-09-01 17:08:14 -0400": {
    "date": "2025-09-01 17:08:14 -0400",
    "type": "daily",
    "hours": 0.5,
    "cost": 150,
    "commits": 1,
    "deployments": 0,
    "filesModified": 1,
    "linesChanged": 14,
    "authors": [
      "SirsiMaster"
    ],
    "technologies": [
      "HTML"
    ],
    "achievements": []
  },
  "2025-09-01 17:11:11 -0400": {
    "date": "2025-09-01 17:11:11 -0400",
    "type": "daily",
    "hours": 0.5,
    "cost": 150,
    "commits": 1,
    "deployments": 0,
    "filesModified": 1,
    "linesChanged": 2,
    "authors": [
      "SirsiMaster"
    ],
    "technologies": [
      "HTML"
    ],
    "achievements": []
  },
  "2025-09-01 17:34:55 -0400": {
    "date": "2025-09-01 17:34:55 -0400",
    "type": "daily",
    "hours": 4,
    "cost": 1200,
    "commits": 1,
    "deployments": 0,
    "filesModified": 15,
    "linesChanged": 941,
    "authors": [
      "SirsiMaster"
    ],
    "technologies": [
      "HTML",
      "GitHub"
    ],
    "achievements": [
      "Major code addition: 1136 lines added"
    ]
  },
  "2025-09-01 17:45:32 -0400": {
    "date": "2025-09-01 17:45:32 -0400",
    "type": "daily",
    "hours": 1,
    "cost": 300,
    "commits": 1,
    "deployments": 0,
    "filesModified": 1,
    "linesChanged": 14,
    "authors": [
      "SirsiMaster"
    ],
    "technologies": [
      "HTML"
    ],
    "achievements": [
      "Feature: add admin index redirect page"
    ]
  },
  "2025-09-01 17:46:38 -0400": {
    "date": "2025-09-01 17:46:38 -0400",
    "type": "daily",
    "hours": 0.5,
    "cost": 150,
    "commits": 1,
    "deployments": 0,
    "filesModified": 1,
    "linesChanged": -14,
    "authors": [
      "SirsiMaster"
    ],
    "technologies": [
      "HTML"
    ],
    "achievements": []
  },
  "2025-09-05 14:03:48 -0400": {
    "date": "2025-09-05 14:03:48 -0400",
    "type": "daily",
    "hours": 4,
    "cost": 1200,
    "commits": 1,
    "deployments": 0,
    "filesModified": 7,
    "linesChanged": 2071,
    "authors": [
      "SirsiMaster"
    ],
    "technologies": [
      "HTML"
    ],
    "achievements": [
      "Major code addition: 2106 lines added"
    ]
  },
  "2025-09-05 14:33:07 -0400": {
    "date": "2025-09-05 14:33:07 -0400",
    "type": "daily",
    "hours": 0.75,
    "cost": 225,
    "commits": 1,
    "deployments": 0,
    "filesModified": 8,
    "linesChanged": 0,
    "authors": [
      "SirsiMaster"
    ],
    "technologies": [
      "HTML"
    ],
    "achievements": []
  },
  "2025-09-05 14:39:24 -0400": {
    "date": "2025-09-05 14:39:24 -0400",
    "type": "daily",
    "hours": 0.925,
    "cost": 278,
    "commits": 1,
    "deployments": 0,
    "filesModified": 1,
    "linesChanged": 185,
    "authors": [
      "SirsiMaster"
    ],
    "technologies": [],
    "achievements": []
  },
  "2025-09-05 15:36:35 -0400": {
    "date": "2025-09-05 15:36:35 -0400",
    "type": "daily",
    "hours": 0.5066666666666667,
    "cost": 152,
    "commits": 1,
    "deployments": 0,
    "filesModified": 7,
    "linesChanged": 0,
    "authors": [
      "SirsiMaster"
    ],
    "technologies": [
      "HTML"
    ],
    "achievements": []
  },
  "2025-09-05 15:42:22 -0400": {
    "date": "2025-09-05 15:42:22 -0400",
    "type": "daily",
    "hours": 0.5,
    "cost": 150,
    "commits": 1,
    "deployments": 0,
    "filesModified": 3,
    "linesChanged": 0,
    "authors": [
      "SirsiMaster"
    ],
    "technologies": [
      "HTML"
    ],
    "achievements": []
  },
  "2025-09-05 15:47:55 -0400": {
    "date": "2025-09-05 15:47:55 -0400",
    "type": "daily",
    "hours": 4,
    "cost": 1200,
    "commits": 1,
    "deployments": 0,
    "filesModified": 39,
    "linesChanged": 0,
    "authors": [
      "SirsiMaster"
    ],
    "technologies": [
      "HTML",
      "CSS"
    ],
    "achievements": []
  },
  "2025-09-05 15:59:21 -0400": {
    "date": "2025-09-05 15:59:21 -0400",
    "type": "daily",
    "hours": 4,
    "cost": 1200,
    "commits": 1,
    "deployments": 0,
    "filesModified": 3,
    "linesChanged": 508,
    "authors": [
      "SirsiMaster"
    ],
    "technologies": [
      "HTML"
    ],
    "achievements": [
      "Feature: Integrate contracts into AssiduousFlip admin"
    ]
  },
  "2025-09-05 16:07:51 -0400": {
    "date": "2025-09-05 16:07:51 -0400",
    "type": "daily",
    "hours": 4,
    "cost": 1200,
    "commits": 1,
    "deployments": 0,
    "filesModified": 10,
    "linesChanged": 345,
    "authors": [
      "SirsiMaster"
    ],
    "technologies": [
      "HTML"
    ],
    "achievements": [
      "Feature: Integrate orphaned Knowledge Base into admin panel"
    ]
  },
  "2025-09-05 16:18:20 -0400": {
    "date": "2025-09-05 16:18:20 -0400",
    "type": "daily",
    "hours": 0.5,
    "cost": 150,
    "commits": 1,
    "deployments": 0,
    "filesModified": 8,
    "linesChanged": -15,
    "authors": [
      "SirsiMaster"
    ],
    "technologies": [
      "HTML"
    ],
    "achievements": []
  },
  "2025-09-05 16:28:38 -0400": {
    "date": "2025-09-05 16:28:38 -0400",
    "type": "daily",
    "hours": 0.5,
    "cost": 150,
    "commits": 1,
    "deployments": 0,
    "filesModified": 1,
    "linesChanged": 34,
    "authors": [
      "SirsiMaster"
    ],
    "technologies": [
      "HTML"
    ],
    "achievements": []
  },
  "2025-09-06 11:37:25 -0400": {
    "date": "2025-09-06 11:37:25 -0400",
    "type": "daily",
    "hours": 4,
    "cost": 1200,
    "commits": 1,
    "deployments": 0,
    "filesModified": 16,
    "linesChanged": -1493,
    "authors": [
      "SirsiMaster"
    ],
    "technologies": [
      "HTML",
      "JavaScript"
    ],
    "achievements": []
  },
  "2025-09-06 12:23:57 -0400": {
    "date": "2025-09-06 12:23:57 -0400",
    "type": "daily",
    "hours": 4,
    "cost": 1200,
    "commits": 1,
    "deployments": 0,
    "filesModified": 10,
    "linesChanged": 3597,
    "authors": [
      "SirsiMaster"
    ],
    "technologies": [],
    "achievements": [
      "Completed: Consolidate implementation into master guide"
    ]
  },
  "2025-09-06 12:29:22 -0400": {
    "date": "2025-09-06 12:29:22 -0400",
    "type": "daily",
    "hours": 2.016,
    "cost": 605,
    "commits": 1,
    "deployments": 1,
    "filesModified": 7,
    "linesChanged": 490,
    "authors": [
      "SirsiMaster"
    ],
    "technologies": [
      "Node.js"
    ],
    "achievements": []
  },
  "2025-09-06 12:37:19 -0400": {
    "date": "2025-09-06 12:37:19 -0400",
    "type": "daily",
    "hours": 4,
    "cost": 1200,
    "commits": 1,
    "deployments": 0,
    "filesModified": 5,
    "linesChanged": 550,
    "authors": [
      "SirsiMaster"
    ],
    "technologies": [
      "GitHub"
    ],
    "achievements": [
      "Feature: Add automated versioning system"
    ]
  },
  "2025-09-06 16:37:35 +0000": {
    "date": "2025-09-06 16:37:35 +0000",
    "type": "daily",
    "hours": 0.25,
    "cost": 75,
    "commits": 1,
    "deployments": 1,
    "filesModified": 4,
    "linesChanged": 13,
    "authors": [
      "github-actions[bot]"
    ],
    "technologies": [
      "Node.js"
    ],
    "achievements": []
  },
  "2025-09-06 12:38:31 -0400": {
    "date": "2025-09-06 12:38:31 -0400",
    "type": "daily",
    "hours": 1.21,
    "cost": 363,
    "commits": 1,
    "deployments": 0,
    "filesModified": 1,
    "linesChanged": 242,
    "authors": [
      "SirsiMaster"
    ],
    "technologies": [],
    "achievements": []
  },
  "2025-09-06 17:34:39 -0400": {
    "date": "2025-09-06 17:34:39 -0400",
    "type": "daily",
    "hours": 4,
    "cost": 1200,
    "commits": 1,
    "deployments": 0,
    "filesModified": 6,
    "linesChanged": 948,
    "authors": [
      "SirsiMaster"
    ],
    "technologies": [
      "HTML",
      "Firebase",
      "JavaScript"
    ],
    "achievements": [
      "Feature: integrate Firebase with development dashboards"
    ]
  },
  "2025-09-06 21:34:55 +0000": {
    "date": "2025-09-06 21:34:55 +0000",
    "type": "daily",
    "hours": 0.25,
    "cost": 75,
    "commits": 1,
    "deployments": 1,
    "filesModified": 4,
    "linesChanged": 13,
    "authors": [
      "github-actions[bot]"
    ],
    "technologies": [
      "Node.js"
    ],
    "achievements": []
  },
  "2025-09-06 18:22:38 -0400": {
    "date": "2025-09-06 18:22:38 -0400",
    "type": "daily",
    "hours": 4,
    "cost": 1200,
    "commits": 1,
    "deployments": 0,
    "filesModified": 2,
    "linesChanged": 1270,
    "authors": [
      "SirsiMaster"
    ],
    "technologies": [
      "HTML",
      "JavaScript"
    ],
    "achievements": [
      "Feature: add comprehensive development cost tracking system"
    ]
  },
  "2025-09-06 22:23:10 +0000": {
    "date": "2025-09-06 22:23:10 +0000",
    "type": "daily",
    "hours": 0.25,
    "cost": 75,
    "commits": 1,
    "deployments": 1,
    "filesModified": 4,
    "linesChanged": 13,
    "authors": [
      "github-actions[bot]"
    ],
    "technologies": [
      "Node.js"
    ],
    "achievements": []
  },
  "2025-09-06 22:24:24 +0000": {
    "date": "2025-09-06 22:24:24 +0000",
    "type": "daily",
    "hours": 0.25,
    "cost": 75,
    "commits": 1,
    "deployments": 1,
    "filesModified": 1,
    "linesChanged": 0,
    "authors": [
      "dependabot[bot]"
    ],
    "technologies": [
      "Node.js"
    ],
    "achievements": []
  },
  "2025-09-06 18:40:09 -0400": {
    "date": "2025-09-06 18:40:09 -0400",
    "type": "daily",
    "hours": 0.5,
    "cost": 150,
    "commits": 1,
    "deployments": 0,
    "filesModified": 0,
    "linesChanged": 0,
    "authors": [
      "SirsiMaster"
    ],
    "technologies": [],
    "achievements": []
  },
  "2025-09-06 18:48:56 -0400": {
    "date": "2025-09-06 18:48:56 -0400",
    "type": "daily",
    "hours": 4,
    "cost": 1200,
    "commits": 1,
    "deployments": 0,
    "filesModified": 1,
    "linesChanged": -245,
    "authors": [
      "SirsiMaster"
    ],
    "technologies": [
      "HTML"
    ],
    "achievements": [
      "Major code addition: 1043 lines added"
    ]
  },
  "2025-09-06 22:49:32 +0000": {
    "date": "2025-09-06 22:49:32 +0000",
    "type": "daily",
    "hours": 0.25,
    "cost": 75,
    "commits": 1,
    "deployments": 1,
    "filesModified": 4,
    "linesChanged": 15,
    "authors": [
      "github-actions[bot]"
    ],
    "technologies": [
      "Node.js"
    ],
    "achievements": []
  },
  "2025-09-06 18:53:53 -0400": {
    "date": "2025-09-06 18:53:53 -0400",
    "type": "daily",
    "hours": 4,
    "cost": 1200,
    "commits": 1,
    "deployments": 1,
    "filesModified": 6,
    "linesChanged": 1575,
    "authors": [
      "SirsiMaster"
    ],
    "technologies": [
      "Firebase",
      "GitHub",
      "HTML",
      "JavaScript"
    ],
    "achievements": [
      "Major code addition: 2999 lines added"
    ]
  },
  "2025-09-06 18:57:22 -0400": {
    "date": "2025-09-06 18:57:22 -0400",
    "type": "daily",
    "hours": 0.5,
    "cost": 150,
    "commits": 1,
    "deployments": 1,
    "filesModified": 1,
    "linesChanged": 8,
    "authors": [
      "SirsiMaster"
    ],
    "technologies": [
      "Firebase",
      "GitHub"
    ],
    "achievements": []
  },
  "2025-09-06 22:57:44 +0000": {
    "date": "2025-09-06 22:57:44 +0000",
    "type": "daily",
    "hours": 0.25,
    "cost": 75,
    "commits": 1,
    "deployments": 1,
    "filesModified": 4,
    "linesChanged": 13,
    "authors": [
      "github-actions[bot]"
    ],
    "technologies": [
      "Node.js"
    ],
    "achievements": []
  },
  "2025-09-06 19:01:12 -0400": {
    "date": "2025-09-06 19:01:12 -0400",
    "type": "daily",
    "hours": 0.5,
    "cost": 150,
    "commits": 1,
    "deployments": 1,
    "filesModified": 1,
    "linesChanged": 1,
    "authors": [
      "SirsiMaster"
    ],
    "technologies": [
      "Firebase",
      "GitHub"
    ],
    "achievements": []
  },
  "2025-09-06 23:01:46 +0000": {
    "date": "2025-09-06 23:01:46 +0000",
    "type": "daily",
    "hours": 0.25,
    "cost": 75,
    "commits": 1,
    "deployments": 1,
    "filesModified": 4,
    "linesChanged": 13,
    "authors": [
      "github-actions[bot]"
    ],
    "technologies": [
      "Node.js"
    ],
    "achievements": []
  },
  "2025-09-06 19:07:19 -0400": {
    "date": "2025-09-06 19:07:19 -0400",
    "type": "daily",
    "hours": 0.5,
    "cost": 150,
    "commits": 1,
    "deployments": 0,
    "filesModified": 1,
    "linesChanged": 0,
    "authors": [
      "SirsiMaster"
    ],
    "technologies": [
      "Firebase",
      "GitHub"
    ],
    "achievements": []
  },
  "2025-09-06 23:07:55 +0000": {
    "date": "2025-09-06 23:07:55 +0000",
    "type": "daily",
    "hours": 0.25,
    "cost": 75,
    "commits": 1,
    "deployments": 1,
    "filesModified": 4,
    "linesChanged": 13,
    "authors": [
      "github-actions[bot]"
    ],
    "technologies": [
      "Node.js"
    ],
    "achievements": []
  },
  "2025-09-06 19:13:58 -0400": {
    "date": "2025-09-06 19:13:58 -0400",
    "type": "daily",
    "hours": 4,
    "cost": 1200,
    "commits": 1,
    "deployments": 0,
    "filesModified": 1,
    "linesChanged": 245,
    "authors": [
      "SirsiMaster"
    ],
    "technologies": [
      "HTML"
    ],
    "achievements": [
      "Major code addition: 1288 lines added"
    ]
  },
  "2025-09-06 23:14:34 +0000": {
    "date": "2025-09-06 23:14:34 +0000",
    "type": "daily",
    "hours": 0.25,
    "cost": 75,
    "commits": 1,
    "deployments": 1,
    "filesModified": 4,
    "linesChanged": 13,
    "authors": [
      "github-actions[bot]"
    ],
    "technologies": [
      "Node.js"
    ],
    "achievements": []
  },
  "2025-09-06 19:19:49 -0400": {
    "date": "2025-09-06 19:19:49 -0400",
    "type": "daily",
    "hours": 0.5,
    "cost": 150,
    "commits": 1,
    "deployments": 0,
    "filesModified": 1,
    "linesChanged": 66,
    "authors": [
      "SirsiMaster"
    ],
    "technologies": [
      "HTML"
    ],
    "achievements": []
  },
  "2025-09-06 23:20:19 +0000": {
    "date": "2025-09-06 23:20:19 +0000",
    "type": "daily",
    "hours": 0.25,
    "cost": 75,
    "commits": 1,
    "deployments": 1,
    "filesModified": 4,
    "linesChanged": 13,
    "authors": [
      "github-actions[bot]"
    ],
    "technologies": [
      "Node.js"
    ],
    "achievements": []
  },
  "2025-09-06 19:26:14 -0400": {
    "date": "2025-09-06 19:26:14 -0400",
    "type": "daily",
    "hours": 4,
    "cost": 1200,
    "commits": 1,
    "deployments": 0,
    "filesModified": 2,
    "linesChanged": 86,
    "authors": [
      "SirsiMaster"
    ],
    "technologies": [
      "HTML"
    ],
    "achievements": [
      "Feature: Add development costs tracking page"
    ]
  },
  "2025-09-06 23:26:39 +0000": {
    "date": "2025-09-06 23:26:39 +0000",
    "type": "daily",
    "hours": 0.25,
    "cost": 75,
    "commits": 1,
    "deployments": 1,
    "filesModified": 4,
    "linesChanged": 13,
    "authors": [
      "github-actions[bot]"
    ],
    "technologies": [
      "Node.js"
    ],
    "achievements": []
  },
  "2025-09-06 19:29:19 -0400": {
    "date": "2025-09-06 19:29:19 -0400",
    "type": "daily",
    "hours": 2.46,
    "cost": 738,
    "commits": 1,
    "deployments": 0,
    "filesModified": 1,
    "linesChanged": 196,
    "authors": [
      "SirsiMaster"
    ],
    "technologies": [
      "HTML"
    ],
    "achievements": [
      "Feature: Add standard admin sidebar to costs page"
    ]
  },
  "2025-09-06 23:29:51 +0000": {
    "date": "2025-09-06 23:29:51 +0000",
    "type": "daily",
    "hours": 0.25,
    "cost": 75,
    "commits": 1,
    "deployments": 1,
    "filesModified": 4,
    "linesChanged": 13,
    "authors": [
      "github-actions[bot]"
    ],
    "technologies": [
      "Node.js"
    ],
    "achievements": []
  },
  "2025-09-06 19:34:18 -0400": {
    "date": "2025-09-06 19:34:18 -0400",
    "type": "daily",
    "hours": 4,
    "cost": 1200,
    "commits": 1,
    "deployments": 1,
    "filesModified": 5,
    "linesChanged": 654,
    "authors": [
      "SirsiMaster"
    ],
    "technologies": [
      "Firebase",
      "GitHub",
      "HTML"
    ],
    "achievements": [
      "Major code addition: 733 lines added"
    ]
  },
  "2025-09-06 23:34:52 +0000": {
    "date": "2025-09-06 23:34:52 +0000",
    "type": "daily",
    "hours": 0.25,
    "cost": 75,
    "commits": 1,
    "deployments": 1,
    "filesModified": 4,
    "linesChanged": 13,
    "authors": [
      "github-actions[bot]"
    ],
    "technologies": [
      "Node.js"
    ],
    "achievements": []
  },
  "2025-09-06 19:38:08 -0400": {
    "date": "2025-09-06 19:38:08 -0400",
    "type": "daily",
    "hours": 0.5,
    "cost": 150,
    "commits": 1,
    "deployments": 0,
    "filesModified": 1,
    "linesChanged": 0,
    "authors": [
      "SirsiMaster"
    ],
    "technologies": [
      "Firebase"
    ],
    "achievements": []
  },
  "2025-09-06 20:15:08 -0400": {
    "date": "2025-09-06 20:15:08 -0400",
    "type": "daily",
    "hours": 4,
    "cost": 1200,
    "commits": 1,
    "deployments": 0,
    "filesModified": 1,
    "linesChanged": -109,
    "authors": [
      "SirsiMaster"
    ],
    "technologies": [
      "HTML"
    ],
    "achievements": [
      "Feature: Restore complete visual metrics"
    ]
  },
  "2025-09-07 00:16:03 +0000": {
    "date": "2025-09-07 00:16:03 +0000",
    "type": "daily",
    "hours": 0.25,
    "cost": 75,
    "commits": 1,
    "deployments": 1,
    "filesModified": 4,
    "linesChanged": 19,
    "authors": [
      "github-actions[bot]"
    ],
    "technologies": [
      "Node.js"
    ],
    "achievements": []
  },
  "2025-09-06 20:25:27 -0400": {
    "date": "2025-09-06 20:25:27 -0400",
    "type": "daily",
    "hours": 1.0875,
    "cost": 326,
    "commits": 1,
    "deployments": 0,
    "filesModified": 2,
    "linesChanged": -63,
    "authors": [
      "SirsiMaster"
    ],
    "technologies": [
      "HTML"
    ],
    "achievements": []
  },
  "2025-09-06 20:32:09 -0400": {
    "date": "2025-09-06 20:32:09 -0400",
    "type": "daily",
    "hours": 4,
    "cost": 1200,
    "commits": 1,
    "deployments": 0,
    "filesModified": 46,
    "linesChanged": 25121,
    "authors": [
      "SirsiMaster"
    ],
    "technologies": [
      "HTML",
      "Firebase",
      "CSS",
      "JavaScript"
    ],
    "achievements": [
      "Major code addition: 25257 lines added"
    ]
  },
  "2025-09-06 20:46:18 -0400": {
    "date": "2025-09-06 20:46:18 -0400",
    "type": "daily",
    "hours": 4,
    "cost": 1200,
    "commits": 1,
    "deployments": 0,
    "filesModified": 12,
    "linesChanged": 2684,
    "authors": [
      "SirsiMaster"
    ],
    "technologies": [
      "Firebase",
      "HTML",
      "JavaScript",
      "GitHub"
    ],
    "achievements": [
      "Major code addition: 3542 lines added"
    ]
  },
  "2025-09-06 20:57:15 -0400": {
    "date": "2025-09-06 20:57:15 -0400",
    "type": "daily",
    "hours": 3.145,
    "cost": 944,
    "commits": 1,
    "deployments": 0,
    "filesModified": 3,
    "linesChanged": 589,
    "authors": [
      "SirsiMaster"
    ],
    "technologies": [
      "Firebase"
    ],
    "achievements": [
      "Major code addition: 609 lines added"
    ]
  },
  "2025-09-06 21:09:40 -0400": {
    "date": "2025-09-06 21:09:40 -0400",
    "type": "daily",
    "hours": 0.665,
    "cost": 200,
    "commits": 1,
    "deployments": 0,
    "filesModified": 2,
    "linesChanged": 1,
    "authors": [
      "SirsiMaster"
    ],
    "technologies": [
      "GitHub"
    ],
    "achievements": []
  },
  "2025-09-06 21:19:42 -0400": {
    "date": "2025-09-06 21:19:42 -0400",
    "type": "daily",
    "hours": 1.5,
    "cost": 450,
    "commits": 1,
    "deployments": 0,
    "filesModified": 2,
    "linesChanged": 2,
    "authors": [
      "SirsiMaster"
    ],
    "technologies": [],
    "achievements": []
  },
  "2025-09-06 21:19:57 -0400": {
    "date": "2025-09-06 21:19:57 -0400",
    "type": "daily",
    "hours": 4,
    "cost": 1200,
    "commits": 1,
    "deployments": 0,
    "filesModified": 9,
    "linesChanged": 1510,
    "authors": [
      "SirsiMaster"
    ],
    "technologies": [
      "JavaScript",
      "GitHub",
      "Firebase"
    ],
    "achievements": [
      "Major code addition: 1525 lines added"
    ]
  },
  "2025-09-06 21:21:44 -0400": {
    "date": "2025-09-06 21:21:44 -0400",
    "type": "daily",
    "hours": 4,
    "cost": 1200,
    "commits": 1,
    "deployments": 0,
    "filesModified": 3,
    "linesChanged": 1082,
    "authors": [
      "SirsiMaster"
    ],
    "technologies": [
      "Firebase",
      "GitHub",
      "JavaScript"
    ],
    "achievements": [
      "Feature: Complete 95% automation for GitHub-to-Firebase pipeline [session:4.0] [cost:$1200]"
    ]
  },
  "2025-09-06 21:32:48 -0400": {
    "date": "2025-09-06 21:32:48 -0400",
    "type": "daily",
    "hours": 0.5,
    "cost": 150,
    "commits": 1,
    "deployments": 0,
    "filesModified": 3,
    "linesChanged": 298,
    "authors": [
      "SirsiMaster"
    ],
    "technologies": [
      "JavaScript",
      "Firebase",
      "GitHub"
    ],
    "achievements": [
      "Feature: Complete 100% automation with webhook configuration [session:0.5] [cost:$150]"
    ]
  },
  "2025-09-06 21:37:14 -0400": {
    "date": "2025-09-06 21:37:14 -0400",
    "type": "daily",
    "hours": 0.5,
    "cost": 150,
    "commits": 1,
    "deployments": 0,
    "filesModified": 3,
    "linesChanged": 368,
    "authors": [
      "SirsiMaster"
    ],
    "technologies": [],
    "achievements": []
  },
  "2025-09-07 01:37:38 +0000": {
    "date": "2025-09-07 01:37:38 +0000",
    "type": "daily",
    "hours": 0.25,
    "cost": 75,
    "commits": 1,
    "deployments": 1,
    "filesModified": 4,
    "linesChanged": 15,
    "authors": [
      "github-actions[bot]"
    ],
    "technologies": [
      "Node.js"
    ],
    "achievements": []
  },
  "2025-09-06 21:43:42 -0400": {
    "date": "2025-09-06 21:43:42 -0400",
    "type": "daily",
    "hours": 1,
    "cost": 300,
    "commits": 1,
    "deployments": 1,
    "filesModified": 1,
    "linesChanged": 414,
    "authors": [
      "SirsiMaster"
    ],
    "technologies": [],
    "achievements": [
      "Feature: Complete Google Cloud CBV system deployment [session:1.0] [cost:$300]"
    ]
  },
  "2025-09-06 21:57:05 -0400": {
    "date": "2025-09-06 21:57:05 -0400",
    "type": "daily",
    "hours": 0.5,
    "cost": 150,
    "commits": 1,
    "deployments": 0,
    "filesModified": 1,
    "linesChanged": 1,
    "authors": [
      "SirsiMaster"
    ],
    "technologies": [],
    "achievements": []
  },
  "2025-09-06 22:18:35 -0400": {
    "date": "2025-09-06 22:18:35 -0400",
    "type": "daily",
    "hours": 2,
    "cost": 600,
    "commits": 1,
    "deployments": 0,
    "filesModified": 1,
    "linesChanged": 117,
    "authors": [
      "SirsiMaster"
    ],
    "technologies": [
      "HTML"
    ],
    "achievements": [
      "Feature: Enterprise security + comprehensive metrics [session:2.0] [cost:]"
    ]
  },
  "2025-09-06 22:19:10 -0400": {
    "date": "2025-09-06 22:19:10 -0400",
    "type": "daily",
    "hours": 0.5,
    "cost": 150,
    "commits": 1,
    "deployments": 0,
    "filesModified": 3,
    "linesChanged": 285,
    "authors": [
      "SirsiMaster"
    ],
    "technologies": [
      "JavaScript",
      "Firebase",
      "GitHub"
    ],
    "achievements": [
      "Feature: Enterprise GitHub webhook security + repo isolation [session:0.5] [cost:]"
    ]
  },
  "2025-09-06 22:22:36 -0400": {
    "date": "2025-09-06 22:22:36 -0400",
    "type": "daily",
    "hours": 0.5,
    "cost": 150,
    "commits": 1,
    "deployments": 0,
    "filesModified": 4,
    "linesChanged": 15,
    "authors": [
      "SirsiMaster"
    ],
    "technologies": [
      "Node.js"
    ],
    "achievements": []
  },
  "2025-09-07 02:23:00 +0000": {
    "date": "2025-09-07 02:23:00 +0000",
    "type": "daily",
    "hours": 0.25,
    "cost": 75,
    "commits": 1,
    "deployments": 1,
    "filesModified": 4,
    "linesChanged": 17,
    "authors": [
      "github-actions[bot]"
    ],
    "technologies": [
      "Node.js"
    ],
    "achievements": []
  },
  "2025-09-06 22:35:43 -0400": {
    "date": "2025-09-06 22:35:43 -0400",
    "type": "daily",
    "hours": 1,
    "cost": 300,
    "commits": 1,
    "deployments": 1,
    "filesModified": 52,
    "linesChanged": 28479,
    "authors": [
      "SirsiMaster"
    ],
    "technologies": [
      "Firebase",
      "GitHub",
      "HTML",
      "JavaScript",
      "CSS"
    ],
    "achievements": [
      "Feature: Complete migration from GitHub Pages to Firebase Hosting [session:1.0] [cost:]"
    ]
  },
  "2025-09-06 22:46:05 -0400": {
    "date": "2025-09-06 22:46:05 -0400",
    "type": "daily",
    "hours": 0.25,
    "cost": 75,
    "commits": 1,
    "deployments": 0,
    "filesModified": 1,
    "linesChanged": 33,
    "authors": [
      "SirsiMaster"
    ],
    "technologies": [
      "Firebase",
      "GitHub"
    ],
    "achievements": []
  },
  "2025-09-06 22:48:54 -0400": {
    "date": "2025-09-06 22:48:54 -0400",
    "type": "daily",
    "hours": 1.41,
    "cost": 423,
    "commits": 1,
    "deployments": 0,
    "filesModified": 4,
    "linesChanged": -83,
    "authors": [
      "SirsiMaster"
    ],
    "technologies": [
      "Firebase",
      "GitHub",
      "Node.js"
    ],
    "achievements": []
  },
  "2025-09-07 02:49:17 +0000": {
    "date": "2025-09-07 02:49:17 +0000",
    "type": "daily",
    "hours": 0.25,
    "cost": 75,
    "commits": 1,
    "deployments": 1,
    "filesModified": 4,
    "linesChanged": 13,
    "authors": [
      "github-actions[bot]"
    ],
    "technologies": [
      "Node.js"
    ],
    "achievements": []
  },
  "2025-09-06 22:57:01 -0400": {
    "date": "2025-09-06 22:57:01 -0400",
    "type": "daily",
    "hours": 1.0066666666666666,
    "cost": 302,
    "commits": 1,
    "deployments": 0,
    "filesModified": 1,
    "linesChanged": -141,
    "authors": [
      "SirsiMaster"
    ],
    "technologies": [
      "HTML"
    ],
    "achievements": []
  },
  "2025-09-06 22:57:16 -0400": {
    "date": "2025-09-06 22:57:16 -0400",
    "type": "daily",
    "hours": 0.5,
    "cost": 150,
    "commits": 1,
    "deployments": 0,
    "filesModified": 4,
    "linesChanged": 13,
    "authors": [
      "SirsiMaster"
    ],
    "technologies": [
      "GitHub",
      "Node.js"
    ],
    "achievements": []
  },
  "2025-09-07 02:58:18 +0000": {
    "date": "2025-09-07 02:58:18 +0000",
    "type": "daily",
    "hours": 0.25,
    "cost": 75,
    "commits": 1,
    "deployments": 1,
    "filesModified": 4,
    "linesChanged": 13,
    "authors": [
      "github-actions[bot]"
    ],
    "technologies": [
      "Node.js"
    ],
    "achievements": []
  },
  "2025-09-06 23:19:36 -0400": {
    "date": "2025-09-06 23:19:36 -0400",
    "type": "daily",
    "hours": 4,
    "cost": 1200,
    "commits": 1,
    "deployments": 0,
    "filesModified": 13,
    "linesChanged": 1097,
    "authors": [
      "SirsiMaster"
    ],
    "technologies": [
      "Firebase",
      "HTML",
      "JavaScript",
      "CSS"
    ],
    "achievements": [
      "Feature: Implement professional standardized admin header system"
    ]
  },
  "2025-09-06 23:19:54 -0400": {
    "date": "2025-09-06 23:19:54 -0400",
    "type": "daily",
    "hours": 0.5,
    "cost": 150,
    "commits": 1,
    "deployments": 0,
    "filesModified": 4,
    "linesChanged": 13,
    "authors": [
      "SirsiMaster"
    ],
    "technologies": [
      "GitHub",
      "Node.js"
    ],
    "achievements": []
  },
  "2025-09-07 03:23:56 +0000": {
    "date": "2025-09-07 03:23:56 +0000",
    "type": "daily",
    "hours": 0.25,
    "cost": 75,
    "commits": 1,
    "deployments": 1,
    "filesModified": 4,
    "linesChanged": 13,
    "authors": [
      "github-actions[bot]"
    ],
    "technologies": [
      "Node.js"
    ],
    "achievements": []
  },
  "2025-09-07 19:12:59 -0400": {
    "date": "2025-09-07 19:12:59 -0400",
    "type": "daily",
    "hours": 4,
    "cost": 1200,
    "commits": 1,
    "deployments": 0,
    "filesModified": 61,
    "linesChanged": 43359,
    "authors": [
      "SirsiMaster"
    ],
    "technologies": [
      "HTML",
      "JavaScript",
      "CSS",
      "Firebase"
    ],
    "achievements": [
      "Feature: Convert markdown documentation to HTML format"
    ]
  },
  "2025-09-07 19:13:44 -0400": {
    "date": "2025-09-07 19:13:44 -0400",
    "type": "daily",
    "hours": 0.5,
    "cost": 150,
    "commits": 1,
    "deployments": 0,
    "filesModified": 4,
    "linesChanged": 13,
    "authors": [
      "SirsiMaster"
    ],
    "technologies": [
      "GitHub",
      "Node.js"
    ],
    "achievements": []
  },
  "2025-09-07 23:14:35 +0000": {
    "date": "2025-09-07 23:14:35 +0000",
    "type": "daily",
    "hours": 0.25,
    "cost": 75,
    "commits": 1,
    "deployments": 1,
    "filesModified": 4,
    "linesChanged": 13,
    "authors": [
      "github-actions[bot]"
    ],
    "technologies": [
      "Node.js"
    ],
    "achievements": []
  },
  "2025-09-07 19:22:40 -0400": {
    "date": "2025-09-07 19:22:40 -0400",
    "type": "daily",
    "hours": 0.5,
    "cost": 150,
    "commits": 1,
    "deployments": 0,
    "filesModified": 1,
    "linesChanged": 0,
    "authors": [
      "SirsiMaster"
    ],
    "technologies": [
      "Firebase",
      "GitHub"
    ],
    "achievements": []
  },
  "2025-09-07 19:23:01 -0400": {
    "date": "2025-09-07 19:23:01 -0400",
    "type": "daily",
    "hours": 0.5,
    "cost": 150,
    "commits": 1,
    "deployments": 0,
    "filesModified": 4,
    "linesChanged": 13,
    "authors": [
      "SirsiMaster"
    ],
    "technologies": [
      "GitHub",
      "Node.js"
    ],
    "achievements": []
  },
  "2025-09-08 00:38:33 +0000": {
    "date": "2025-09-08 00:38:33 +0000",
    "type": "daily",
    "hours": 0.25,
    "cost": 75,
    "commits": 1,
    "deployments": 1,
    "filesModified": 4,
    "linesChanged": 13,
    "authors": [
      "github-actions[bot]"
    ],
    "technologies": [
      "Node.js"
    ],
    "achievements": []
  },
  "2025-09-07 20:40:46 -0400": {
    "date": "2025-09-07 20:40:46 -0400",
    "type": "daily",
    "hours": 0.5,
    "cost": 150,
    "commits": 1,
    "deployments": 0,
    "filesModified": 1,
    "linesChanged": 16,
    "authors": [
      "SirsiMaster"
    ],
    "technologies": [
      "HTML",
      "Firebase",
      "GitHub"
    ],
    "achievements": []
  },
  "2025-09-07 20:41:03 -0400": {
    "date": "2025-09-07 20:41:03 -0400",
    "type": "daily",
    "hours": 0.5,
    "cost": 150,
    "commits": 1,
    "deployments": 0,
    "filesModified": 4,
    "linesChanged": 13,
    "authors": [
      "SirsiMaster"
    ],
    "technologies": [
      "GitHub",
      "Node.js"
    ],
    "achievements": []
  },
  "2025-09-07 20:55:01 -0400": {
    "date": "2025-09-07 20:55:01 -0400",
    "type": "daily",
    "hours": 0.5,
    "cost": 150,
    "commits": 1,
    "deployments": 1,
    "filesModified": 1,
    "linesChanged": 0,
    "authors": [
      "SirsiMaster"
    ],
    "technologies": [
      "GitHub"
    ],
    "achievements": []
  },
  "2025-09-08 00:55:27 +0000": {
    "date": "2025-09-08 00:55:27 +0000",
    "type": "daily",
    "hours": 0.25,
    "cost": 75,
    "commits": 1,
    "deployments": 1,
    "filesModified": 4,
    "linesChanged": 13,
    "authors": [
      "github-actions[bot]"
    ],
    "technologies": [
      "Node.js"
    ],
    "achievements": []
  },
  "2025-09-07 21:05:28 -0400": {
    "date": "2025-09-07 21:05:28 -0400",
    "type": "daily",
    "hours": 0.5,
    "cost": 150,
    "commits": 1,
    "deployments": 1,
    "filesModified": 1,
    "linesChanged": 19,
    "authors": [
      "SirsiMaster"
    ],
    "technologies": [
      "JavaScript",
      "Firebase"
    ],
    "achievements": []
  },
  "2025-09-07 21:05:52 -0400": {
    "date": "2025-09-07 21:05:52 -0400",
    "type": "daily",
    "hours": 0.5,
    "cost": 150,
    "commits": 1,
    "deployments": 0,
    "filesModified": 4,
    "linesChanged": 13,
    "authors": [
      "SirsiMaster"
    ],
    "technologies": [
      "GitHub",
      "Node.js"
    ],
    "achievements": []
  },
  "2025-09-08 01:07:14 +0000": {
    "date": "2025-09-08 01:07:14 +0000",
    "type": "daily",
    "hours": 0.25,
    "cost": 75,
    "commits": 1,
    "deployments": 1,
    "filesModified": 4,
    "linesChanged": 13,
    "authors": [
      "github-actions[bot]"
    ],
    "technologies": [
      "Node.js"
    ],
    "achievements": []
  },
  "2025-09-07 21:17:00 -0400": {
    "date": "2025-09-07 21:17:00 -0400",
    "type": "daily",
    "hours": 0.5,
    "cost": 150,
    "commits": 1,
    "deployments": 0,
    "filesModified": 1,
    "linesChanged": 0,
    "authors": [
      "SirsiMaster"
    ],
    "technologies": [
      "Firebase"
    ],
    "achievements": []
  },
  "2025-09-07 21:17:17 -0400": {
    "date": "2025-09-07 21:17:17 -0400",
    "type": "daily",
    "hours": 0.5,
    "cost": 150,
    "commits": 1,
    "deployments": 0,
    "filesModified": 4,
    "linesChanged": 13,
    "authors": [
      "SirsiMaster"
    ],
    "technologies": [
      "GitHub",
      "Node.js"
    ],
    "achievements": []
  },
  "2025-09-08 01:17:55 +0000": {
    "date": "2025-09-08 01:17:55 +0000",
    "type": "daily",
    "hours": 0.25,
    "cost": 75,
    "commits": 1,
    "deployments": 1,
    "filesModified": 4,
    "linesChanged": 13,
    "authors": [
      "github-actions[bot]"
    ],
    "technologies": [
      "Node.js"
    ],
    "achievements": []
  },
  "2025-09-07 21:21:10 -0400": {
    "date": "2025-09-07 21:21:10 -0400",
    "type": "daily",
    "hours": 0.5,
    "cost": 150,
    "commits": 2,
    "deployments": 0,
    "filesModified": 1,
    "linesChanged": 80,
    "authors": [
      "SirsiMaster"
    ],
    "technologies": [
      "JavaScript"
    ],
    "achievements": []
  },
  "2025-09-07 22:17:04 -0400": {
    "date": "2025-09-07 22:17:04 -0400",
    "type": "daily",
    "hours": 0.5,
    "cost": 150,
    "commits": 1,
    "deployments": 0,
    "filesModified": 1,
    "linesChanged": 24,
    "authors": [
      "SirsiMaster"
    ],
    "technologies": [
      "HTML",
      "Firebase"
    ],
    "achievements": []
  },
  "2025-09-08 02:19:28 +0000": {
    "date": "2025-09-08 02:19:28 +0000",
    "type": "daily",
    "hours": 0.25,
    "cost": 75,
    "commits": 1,
    "deployments": 1,
    "filesModified": 4,
    "linesChanged": 13,
    "authors": [
      "github-actions[bot]"
    ],
    "technologies": [
      "Node.js"
    ],
    "achievements": []
  },
  "2025-09-07 22:24:28 -0400": {
    "date": "2025-09-07 22:24:28 -0400",
    "type": "daily",
    "hours": 0.5,
    "cost": 150,
    "commits": 2,
    "deployments": 0,
    "filesModified": 1,
    "linesChanged": 50,
    "authors": [
      "SirsiMaster"
    ],
    "technologies": [
      "HTML"
    ],
    "achievements": []
  },
  "2025-09-07 22:24:52 -0400": {
    "date": "2025-09-07 22:24:52 -0400",
    "type": "daily",
    "hours": 0.5,
    "cost": 150,
    "commits": 2,
    "deployments": 0,
    "filesModified": 1,
    "linesChanged": 0,
    "authors": [
      "SirsiMaster"
    ],
    "technologies": [],
    "achievements": []
  },
  "2025-09-08 02:25:18 +0000": {
    "date": "2025-09-08 02:25:18 +0000",
    "type": "daily",
    "hours": 0.25,
    "cost": 75,
    "commits": 1,
    "deployments": 1,
    "filesModified": 4,
    "linesChanged": 13,
    "authors": [
      "github-actions[bot]"
    ],
    "technologies": [
      "Node.js"
    ],
    "achievements": []
  },
  "2025-09-07 22:31:12 -0400": {
    "date": "2025-09-07 22:31:12 -0400",
    "type": "daily",
    "hours": 0.7133333333333334,
    "cost": 214,
    "commits": 1,
    "deployments": 0,
    "filesModified": 1,
    "linesChanged": 13,
    "authors": [
      "SirsiMaster"
    ],
    "technologies": [
      "HTML"
    ],
    "achievements": []
  },
  "2025-09-08 02:31:53 +0000": {
    "date": "2025-09-08 02:31:53 +0000",
    "type": "daily",
    "hours": 0.25,
    "cost": 75,
    "commits": 1,
    "deployments": 1,
    "filesModified": 4,
    "linesChanged": 13,
    "authors": [
      "github-actions[bot]"
    ],
    "technologies": [
      "Node.js"
    ],
    "achievements": []
  },
  "2025-09-07 22:37:28 -0400": {
    "date": "2025-09-07 22:37:28 -0400",
    "type": "daily",
    "hours": 0.5,
    "cost": 150,
    "commits": 1,
    "deployments": 1,
    "filesModified": 1,
    "linesChanged": 0,
    "authors": [
      "SirsiMaster"
    ],
    "technologies": [
      "Firebase"
    ],
    "achievements": []
  },
  "2025-09-08 02:38:06 +0000": {
    "date": "2025-09-08 02:38:06 +0000",
    "type": "daily",
    "hours": 0.25,
    "cost": 75,
    "commits": 1,
    "deployments": 1,
    "filesModified": 4,
    "linesChanged": 13,
    "authors": [
      "github-actions[bot]"
    ],
    "technologies": [
      "Node.js"
    ],
    "achievements": []
  },
  "2025-09-07 22:41:50 -0400": {
    "date": "2025-09-07 22:41:50 -0400",
    "type": "daily",
    "hours": 0.5,
    "cost": 150,
    "commits": 1,
    "deployments": 1,
    "filesModified": 2,
    "linesChanged": 2,
    "authors": [
      "SirsiMaster"
    ],
    "technologies": [
      "Firebase",
      "GitHub",
      "HTML"
    ],
    "achievements": []
  },
  "2025-09-08 02:42:28 +0000": {
    "date": "2025-09-08 02:42:28 +0000",
    "type": "daily",
    "hours": 0.25,
    "cost": 75,
    "commits": 1,
    "deployments": 1,
    "filesModified": 4,
    "linesChanged": 13,
    "authors": [
      "github-actions[bot]"
    ],
    "technologies": [
      "Node.js"
    ],
    "achievements": []
  },
  "2025-09-07 22:50:04 -0400": {
    "date": "2025-09-07 22:50:04 -0400",
    "type": "daily",
    "hours": 0.5,
    "cost": 150,
    "commits": 1,
    "deployments": 0,
    "filesModified": 1,
    "linesChanged": 1,
    "authors": [
      "SirsiMaster"
    ],
    "technologies": [
      "HTML"
    ],
    "achievements": []
  },
  "2025-09-07 22:51:03 -0400": {
    "date": "2025-09-07 22:51:03 -0400",
    "type": "daily",
    "hours": 0.5,
    "cost": 150,
    "commits": 1,
    "deployments": 0,
    "filesModified": 1,
    "linesChanged": 42,
    "authors": [
      "SirsiMaster"
    ],
    "technologies": [
      "HTML"
    ],
    "achievements": []
  },
  "2025-09-07 22:51:30 -0400": {
    "date": "2025-09-07 22:51:30 -0400",
    "type": "daily",
    "hours": 4,
    "cost": 1200,
    "commits": 1,
    "deployments": 1,
    "filesModified": 87,
    "linesChanged": 27448,
    "authors": [
      "SirsiMaster"
    ],
    "technologies": [
      "Firebase",
      "HTML",
      "CSS",
      "JavaScript",
      "GitHub"
    ],
    "achievements": [
      "Major code addition: 30300 lines added"
    ]
  },
  "2025-09-07 23:26:29 -0400": {
    "date": "2025-09-07 23:26:29 -0400",
    "type": "daily",
    "hours": 4,
    "cost": 1200,
    "commits": 1,
    "deployments": 0,
    "filesModified": 20,
    "linesChanged": -2181,
    "authors": [
      "SirsiMaster"
    ],
    "technologies": [
      "Firebase",
      "HTML",
      "JavaScript"
    ],
    "achievements": []
  },
  "2025-09-08 03:26:51 +0000": {
    "date": "2025-09-08 03:26:51 +0000",
    "type": "daily",
    "hours": 0.25,
    "cost": 75,
    "commits": 1,
    "deployments": 1,
    "filesModified": 4,
    "linesChanged": 17,
    "authors": [
      "github-actions[bot]"
    ],
    "technologies": [
      "Node.js"
    ],
    "achievements": []
  },
  "2025-09-07 23:35:18 -0400": {
    "date": "2025-09-07 23:35:18 -0400",
    "type": "daily",
    "hours": 4,
    "cost": 1200,
    "commits": 1,
    "deployments": 0,
    "filesModified": 118,
    "linesChanged": -23667,
    "authors": [
      "SirsiMaster"
    ],
    "technologies": [
      "HTML",
      "Firebase",
      "JavaScript",
      "CSS"
    ],
    "achievements": [
      "Major code addition: 3051 lines added"
    ]
  },
  "2025-09-07 23:35:38 -0400": {
    "date": "2025-09-07 23:35:38 -0400",
    "type": "daily",
    "hours": 0.5,
    "cost": 150,
    "commits": 1,
    "deployments": 0,
    "filesModified": 4,
    "linesChanged": 17,
    "authors": [
      "SirsiMaster"
    ],
    "technologies": [
      "GitHub",
      "Node.js"
    ],
    "achievements": []
  },
  "2025-09-07 23:36:49 -0400": {
    "date": "2025-09-07 23:36:49 -0400",
    "type": "daily",
    "hours": 0.57,
    "cost": 171,
    "commits": 1,
    "deployments": 0,
    "filesModified": 1,
    "linesChanged": 114,
    "authors": [
      "SirsiMaster"
    ],
    "technologies": [],
    "achievements": []
  },
  "2025-09-07 23:40:46 -0400": {
    "date": "2025-09-07 23:40:46 -0400",
    "type": "daily",
    "hours": 2.1066666666666665,
    "cost": 632,
    "commits": 1,
    "deployments": 0,
    "filesModified": 16,
    "linesChanged": 274,
    "authors": [
      "SirsiMaster"
    ],
    "technologies": [
      "Firebase",
      "HTML"
    ],
    "achievements": []
  },
  "2025-09-08 03:41:08 +0000": {
    "date": "2025-09-08 03:41:08 +0000",
    "type": "daily",
    "hours": 0.25,
    "cost": 75,
    "commits": 1,
    "deployments": 1,
    "filesModified": 4,
    "linesChanged": 13,
    "authors": [
      "github-actions[bot]"
    ],
    "technologies": [
      "Node.js"
    ],
    "achievements": []
  },
  "2025-09-07 23:47:25 -0400": {
    "date": "2025-09-07 23:47:25 -0400",
    "type": "daily",
    "hours": 3.1666666666666665,
    "cost": 950,
    "commits": 1,
    "deployments": 0,
    "filesModified": 12,
    "linesChanged": 161,
    "authors": [
      "SirsiMaster"
    ],
    "technologies": [
      "Firebase",
      "JavaScript",
      "HTML"
    ],
    "achievements": []
  },
  "2025-09-07 23:47:45 -0400": {
    "date": "2025-09-07 23:47:45 -0400",
    "type": "daily",
    "hours": 0.5,
    "cost": 150,
    "commits": 1,
    "deployments": 0,
    "filesModified": 4,
    "linesChanged": 13,
    "authors": [
      "SirsiMaster"
    ],
    "technologies": [
      "GitHub",
      "Node.js"
    ],
    "achievements": []
  },
  "2025-09-08 03:48:03 +0000": {
    "date": "2025-09-08 03:48:03 +0000",
    "type": "daily",
    "hours": 0.25,
    "cost": 75,
    "commits": 1,
    "deployments": 1,
    "filesModified": 4,
    "linesChanged": 13,
    "authors": [
      "github-actions[bot]"
    ],
    "technologies": [
      "Node.js"
    ],
    "achievements": []
  },
  "2025-09-07 23:50:30 -0400": {
    "date": "2025-09-07 23:50:30 -0400",
    "type": "daily",
    "hours": 1.7066666666666668,
    "cost": 512,
    "commits": 1,
    "deployments": 0,
    "filesModified": 6,
    "linesChanged": 162,
    "authors": [
      "SirsiMaster"
    ],
    "technologies": [
      "Firebase",
      "HTML"
    ],
    "achievements": []
  },
  "2025-09-07 23:50:54 -0400": {
    "date": "2025-09-07 23:50:54 -0400",
    "type": "daily",
    "hours": 0.5,
    "cost": 150,
    "commits": 1,
    "deployments": 0,
    "filesModified": 4,
    "linesChanged": 13,
    "authors": [
      "SirsiMaster"
    ],
    "technologies": [
      "GitHub",
      "Node.js"
    ],
    "achievements": []
  },
  "2025-09-08 03:51:08 +0000": {
    "date": "2025-09-08 03:51:08 +0000",
    "type": "daily",
    "hours": 0.25,
    "cost": 75,
    "commits": 1,
    "deployments": 1,
    "filesModified": 4,
    "linesChanged": 13,
    "authors": [
      "github-actions[bot]"
    ],
    "technologies": [
      "Node.js"
    ],
    "achievements": []
  },
  "2025-09-07 23:54:31 -0400": {
    "date": "2025-09-07 23:54:31 -0400",
    "type": "daily",
    "hours": 1.1333333333333333,
    "cost": 340,
    "commits": 1,
    "deployments": 0,
    "filesModified": 7,
    "linesChanged": 34,
    "authors": [
      "SirsiMaster"
    ],
    "technologies": [
      "Firebase",
      "JavaScript"
    ],
    "achievements": []
  },
  "2025-09-07 23:54:53 -0400": {
    "date": "2025-09-07 23:54:53 -0400",
    "type": "daily",
    "hours": 0.5,
    "cost": 150,
    "commits": 1,
    "deployments": 0,
    "filesModified": 4,
    "linesChanged": 13,
    "authors": [
      "SirsiMaster"
    ],
    "technologies": [
      "GitHub",
      "Node.js"
    ],
    "achievements": []
  },
  "2025-09-08 03:55:08 +0000": {
    "date": "2025-09-08 03:55:08 +0000",
    "type": "daily",
    "hours": 0.25,
    "cost": 75,
    "commits": 1,
    "deployments": 1,
    "filesModified": 4,
    "linesChanged": 13,
    "authors": [
      "github-actions[bot]"
    ],
    "technologies": [
      "Node.js"
    ],
    "achievements": []
  },
  "2025-09-07 23:57:18 -0400": {
    "date": "2025-09-07 23:57:18 -0400",
    "type": "daily",
    "hours": 1.2133333333333334,
    "cost": 364,
    "commits": 1,
    "deployments": 0,
    "filesModified": 7,
    "linesChanged": 48,
    "authors": [
      "SirsiMaster"
    ],
    "technologies": [
      "Firebase",
      "JavaScript"
    ],
    "achievements": []
  },
  "2025-09-07 23:57:37 -0400": {
    "date": "2025-09-07 23:57:37 -0400",
    "type": "daily",
    "hours": 0.5,
    "cost": 150,
    "commits": 1,
    "deployments": 0,
    "filesModified": 4,
    "linesChanged": 13,
    "authors": [
      "SirsiMaster"
    ],
    "technologies": [
      "GitHub",
      "Node.js"
    ],
    "achievements": []
  },
  "2025-09-08 03:57:54 +0000": {
    "date": "2025-09-08 03:57:54 +0000",
    "type": "daily",
    "hours": 0.25,
    "cost": 75,
    "commits": 1,
    "deployments": 1,
    "filesModified": 4,
    "linesChanged": 13,
    "authors": [
      "github-actions[bot]"
    ],
    "technologies": [
      "Node.js"
    ],
    "achievements": []
  },
  "2025-09-08 00:09:08 -0400": {
    "date": "2025-09-08 00:09:08 -0400",
    "type": "daily",
    "hours": 0.5,
    "cost": 150,
    "commits": 1,
    "deployments": 0,
    "filesModified": 2,
    "linesChanged": 0,
    "authors": [
      "SirsiMaster"
    ],
    "technologies": [
      "Firebase",
      "HTML"
    ],
    "achievements": []
  },
  "2025-09-08 04:10:45 +0000": {
    "date": "2025-09-08 04:10:45 +0000",
    "type": "daily",
    "hours": 0.25,
    "cost": 75,
    "commits": 1,
    "deployments": 1,
    "filesModified": 4,
    "linesChanged": 13,
    "authors": [
      "github-actions[bot]"
    ],
    "technologies": [
      "Node.js"
    ],
    "achievements": []
  },
  "2025-09-08 00:21:42 -0400": {
    "date": "2025-09-08 00:21:42 -0400",
    "type": "daily",
    "hours": 4,
    "cost": 1200,
    "commits": 1,
    "deployments": 0,
    "filesModified": 170,
    "linesChanged": 10099,
    "authors": [
      "SirsiMaster"
    ],
    "technologies": [
      "Firebase",
      "GitHub",
      "JavaScript",
      "HTML",
      "Node.js"
    ],
    "achievements": [
      "Major code addition: 13404 lines added"
    ]
  },
  "2025-09-08 00:29:11 -0400": {
    "date": "2025-09-08 00:29:11 -0400",
    "type": "daily",
    "hours": 1.36,
    "cost": 408,
    "commits": 1,
    "deployments": 0,
    "filesModified": 4,
    "linesChanged": 2,
    "authors": [
      "SirsiMaster"
    ],
    "technologies": [
      "Firebase",
      "HTML",
      "Node.js"
    ],
    "achievements": []
  },
  "2025-09-08 00:38:42 -0400": {
    "date": "2025-09-08 00:38:42 -0400",
    "type": "daily",
    "hours": 2.69,
    "cost": 807,
    "commits": 1,
    "deployments": 0,
    "filesModified": 4,
    "linesChanged": 69,
    "authors": [
      "SirsiMaster"
    ],
    "technologies": [
      "Firebase",
      "HTML",
      "JavaScript"
    ],
    "achievements": [
      "Feature: add smart breadcrumb navigation and back button to admin pages"
    ]
  },
  "2025-09-08 00:46:37 -0400": {
    "date": "2025-09-08 00:46:37 -0400",
    "type": "daily",
    "hours": 4,
    "cost": 1200,
    "commits": 1,
    "deployments": 0,
    "filesModified": 5,
    "linesChanged": 145,
    "authors": [
      "SirsiMaster"
    ],
    "technologies": [
      "Firebase",
      "JavaScript",
      "HTML"
    ],
    "achievements": []
  }
}